thingserver/__init__.py
thingserver/action.py
thingserver/errors.py
thingserver/event.py
thingserver/json.py
thingserver/property.py
thingserver/server.py
thingserver/subscriber.py
thingserver/thing.py
thingserver/utils.py
thingserver/value.py
thingserver-0.2.1.dist-info/LICENSE.txt
thingserver-0.2.1.dist-info/WHEEL
thingserver-0.2.1.dist-info/METADATA
thingserver-0.2.1.dist-info/RECORD
