Metadata-Version: 2.1
Name: thingserver
Version: 0.2.1
Summary: HTTP Web Thing implementation
License: MPL-2.0
Author: Joel Collins
Author-email: joel@jtcollins.net
Requires-Python: >=3.6,<4.0
Classifier: Development Status :: 4 - Beta
Classifier: Intended Audience :: Developers
Classifier: License :: OSI Approved
Classifier: License :: OSI Approved :: Mozilla Public License 2.0 (MPL 2.0)
Classifier: Programming Language :: Python :: 3
Classifier: Programming Language :: Python :: 3.6
Classifier: Programming Language :: Python :: 3.7
Classifier: Programming Language :: Python :: 3.8
Requires-Dist: ifaddr (>=0.1.7,<0.2.0)
Requires-Dist: jsonschema (>=3.2.0,<4.0.0)
Requires-Dist: pyee (>=7.0.2,<8.0.0)
Requires-Dist: tornado (>=6.0.4,<7.0.0)
Requires-Dist: zeroconf (>=0.28.3,<0.29.0)
